{
  "basics": {
    "name": "Solyee Han",
    "label": "Student",
    "picture": "https://github.com/solyeeh.png",
    "email": "solyee@hawaii.edu",
    "phone": "808-384-8455",
    "website": "https://solyeeh.github.io",
    "summary": "I am studying for a B.S. in Computer Science in the Department of Information and Computer Sciences at the University of Hawaii. I expect to graduate in Spring, 2025.",
    "location": { "address": "", "postalCode": "96816", "city": "Honolulu", "countryCode": "USA", "region": "Hawaii" },
    "profiles": [
      { "network": "github", "username": "solyee", "url": "http://github.com/solyeeh" },
      { "network": "linkedin", "username": "solyee", "url": "http://linkedin.com/in/" },
      { "network": "twitter", "username": "solyee", "url": "http://twitter.com/" },
      { "network": "instagram", "username": "solyee", "url": "http://instagram.com/" }
    ]
  },
  "interests": [
    { "name": "Software engineering" },
    { "name": "Computer science" },
    { "name": "Video games" },
    { "name": "Reading" },
    { "name": "Baking" }
  ],
  "skills": [
    {
      "name": "Languages and Frameworks",
      "keywords": [ "Java", "Javascript", "jGrasp" ]
    },
    {
      "name": "Toolsets/OS",
      "keywords": [ "Git/GitHub", "Windows" ]
    }
  ],
  "education": [
    {
      "institution": "University of Hawaii, Honolulu, HI",
      "area": "Computer Science (expected Spring, 2025)",
      "studyType": "B.S.",
      "startDate": "2022-09-01",
      "endDate": "Present",
      "courses": [
      ]
    }
  ],
  "work": [
    {
      "company": "Pai Cafe",
      "position": "Baker",
      "website": "",
      "startDate": "2024-01-10",
      "endDate": "Present",
      "summary": "Prepare and bake food items required",
      "highlights": [
        "Follow the company's recipe for pastries and baked goods"
        
      ]
    },
    {
      "company": "Moku Kitchen",
      "position": "Lead baker",
      "website": "",
      "startDate": "2016-010-01",
      "endDate": "2019-10-01",
      "summary": "Responsible for Moku's bakeshop",
      "highlights": [
        "Creative ideas for monthly special pies" , "In charge of bakeshop and scheduling"
        
      ]
    }
  ],
 
  "references": [
    {
      "name": "Available upon request"
    }
  ]
}
